{"v":"5.12.1","fr":60,"ip":0,"op":221,"w":430,"h":430,"nm":"wired-outline-2077-hacking","ddd":0,"assets":[{"id":"comp_0","nm":"in-reveal","fr":60,"layers":[{"ddd":0,"ind":1,"ty":4,"nm":"laptop","sr":1,"ks":{"o":{"a":0,"k":100,"ix":11},"r":{"a":0,"k":0,"ix":10},"p":{"a":1,"k":[{"i":{"x":0.501,"y":1},"o":{"x":0.167,"y":0.167},"t":48,"s":[215,392.892,0],"to":[0,0,0],"ti":[0,0,0]},{"i":{"x":0.667,"y":1},"o":{"x":0.333,"y":0},"t":63.75,"s":[215,372.892,0],"to":[0,0,0],"ti":[0,0,0]},{"t":90,"s":[215,387.892,0]}],"ix":2,"l":2},"a":{"a":1,"k":[{"i":{"x":0.833,"y":0.833},"o":{"x":0.167,"y":0.167},"t":48,"s":[250,422.854,0],"to":[0,0,0],"ti":[0,0,0]},{"i":{"x":0.833,"y":0.833},"o":{"x":0.167,"y":0.167},"t":67.25,"s":[250,422.854,0],"to":[0,0,0],"ti":[0,0,0]},{"t":90,"s":[250,422.854,0]}],"ix":1,"l":2},"s":{"a":1,"k":[{"i":{"x":[0.568,0.46,0.667],"y":[1,1,1]},"o":{"x":[0.167,0.167,0.167],"y":[0,0.167,0]},"t":48,"s":[100,100,100]},{"i":{"x":[0.667,0.667,0.667],"y":[1,1,1]},"o":{"x":[0.333,0.333,0.333],"y":[0,0,0]},"t":67.25,"s":[100,107,100]},{"t":90,"s":[100,100,100]}],"ix":6,"l":2}},"ao":0,"shapes":[{"ty":"gr","it":[{"ind":0,"ty":"sh","ix":1,"ks":{"a":1,"k":[{"i":{"x":0.833,"y":0.833},"o":{"x":0.167,"y":0.167},"t":48,"s":[{"i":[[0,-0.022],[8.092,0],[0,0.022],[-8.092,0]],"o":[[0,0.022],[-8.092,0],[0,-0.022],[8.092,0]],"v":[[14.614,91.096],[-0.038,91.136],[-14.69,91.096],[-0.038,91.055]],"c":true}]},{"i":{"x":0.667,"y":1},"o":{"x":0.167,"y":0.167},"t":53.25,"s":[{"i":[[0,-8.092],[8.092,0],[0,8.092],[-8.092,0]],"o":[[0,8.092],[-8.092,0],[0,-8.092],[8.092,0]],"v":[[14.614,50.5],[-0.038,65.152],[-14.69,50.5],[-0.038,35.848]],"c":true}]},{"i":{"x":0.667,"y":1},"o":{"x":0.333,"y":0},"t":67.25,"s":[{"i":[[0,-8.092],[8.092,0],[0,8.092],[-8.092,0]],"o":[[0,8.092],[-8.092,0],[0,-8.092],[8.092,0]],"v":[[14.652,0],[0,14.652],[-14.652,0],[0,-14.652]],"c":true}]},{"t":90,"s":[{"i":[[0,-8.092],[8.092,0],[0,8.092],[-8.092,0]],"o":[[0,8.092],[-8.092,0],[0,-8.092],[8.092,0]],"v":[[14.652,0],[0,14.652],[-14.652,0],[0,-14.652]],"c":true}]}],"ix":2},"nm":"Path 1","mn":"ADBE Vector Shape - Group","hd":false},{"ty":"st","c":{"a":0,"k":[0.031372550875,0.658823549747,0.541176497936,1],"ix":3,"x":"var $bm_rt;\n$bm_rt = comp('wired-outline-2077-hacking').layer('control').effect('secondary')('Color');"},"o":{"a":0,"k":100,"ix":4},"w":{"a":0,"k":12,"ix":5,"x":"var $bm_rt;\n$bm_rt = $bm_mul($bm_div(value, 2), comp('wired-outline-2077-hacking').layer('control').effect('stroke')('Menu'));"},"lc":2,"lj":2,"bm":0,"nm":".secondary","mn":"ADBE Vector Graphic - Stroke","hd":false,"cl":"secondary"},{"ty":"tr","p":{"a":0,"k":[250,332.698],"ix":2},"a":{"a":0,"k":[0,0],"ix":1},"s":{"a":0,"k":[100,100],"ix":3},"r":{"a":0,"k":0,"ix":6},"o":{"a":0,"k":100,"ix":7},"sk":{"a":0,"k":0,"ix":4},"sa":{"a":0,"k":0,"ix":5},"nm":"Transform"}],"nm":"Group 1","np":2,"cix":2,"bm":0,"ix":1,"mn":"ADBE Vector Group","hd":false},{"ty":"gr","it":[{"ty":"gr","it":[{"ind":0,"ty":"sh","ix":1,"ks":{"a":1,"k":[{"i":{"x":0.833,"y":0.833},"o":{"x":0.167,"y":0.167},"t":48,"s":[{"i":[[0,0],[0,0],[0,0],[-6.901,0],[0,0],[0.411,-0.019]],"o":[[0,0],[0,0],[-0.411,-0.019],[0,0],[6.901,0],[0,0]],"v":[[84.025,85.673],[-84.025,85.673],[-84.542,85.621],[-72.576,85.586],[72.166,85.586],[84.133,85.621]],"c":true}]},{"i":{"x":0.667,"y":1},"o":{"x":0.167,"y":0.167},"t":53.25,"s":[{"i":[[0,0],[0,0],[0,0],[-6.901,0],[0,0],[0.411,-6.889]],"o":[[0,0],[0,0],[-0.411,-6.889],[0,0],[6.901,0],[0,0]],"v":[[84.025,60.287],[-84.025,60.287],[-84.542,41.828],[-72.576,29.127],[72.166,29.127],[84.133,41.828]],"c":true}]},{"i":{"x":0.667,"y":1},"o":{"x":0.333,"y":0},"t":67.25,"s":[{"i":[[0,0],[0,0],[0,0],[-6.901,0],[0,0],[0.411,-6.889]],"o":[[0,0],[0,0],[-0.411,-6.889],[0,0],[6.901,0],[0,0]],"v":[[84.025,60.287],[-84.025,60.287],[-90.462,-47.586],[-78.496,-60.287],[78.496,-60.287],[90.462,-47.586]],"c":true}]},{"t":90,"s":[{"i":[[0,0],[0,0],[0,0],[-6.901,0],[0,0],[0.411,-6.889]],"o":[[0,0],[0,0],[-0.411,-6.889],[0,0],[6.901,0],[0,0]],"v":[[84.025,60.287],[-84.025,60.287],[-90.462,-47.586],[-78.496,-60.287],[78.496,-60.287],[90.462,-47.586]],"c":true}]}],"ix":2},"nm":"Path 1","mn":"ADBE Vector Shape - Group","hd":false},{"ty":"st","c":{"a":0,"k":[0.031372550875,0.658823549747,0.541176497936,1],"ix":3,"x":"var $bm_rt;\n$bm_rt = comp('wired-outline-2077-hacking').layer('control').effect('secondary')('Color');"},"o":{"a":0,"k":100,"ix":4},"w":{"a":0,"k":12,"ix":5,"x":"var $bm_rt;\n$bm_rt = $bm_mul($bm_div(value, 2), comp('wired-outline-2077-hacking').layer('control').effect('stroke')('Menu'));"},"lc":2,"lj":2,"bm":0,"nm":".secondary","mn":"ADBE Vector Graphic - Stroke","hd":false,"cl":"secondary"},{"ty":"tr","p":{"a":0,"k":[250,338.164],"ix":2},"a":{"a":0,"k":[0,0],"ix":1},"s":{"a":0,"k":[100,100],"ix":3},"r":{"a":0,"k":0,"ix":6},"o":{"a":0,"k":100,"ix":7},"sk":{"a":0,"k":0,"ix":4},"sa":{"a":0,"k":0,"ix":5},"nm":"Transform"}],"nm":"Group 1","np":2,"cix":2,"bm":0,"ix":1,"mn":"ADBE Vector Group","hd":false},{"ty":"gr","it":[{"ind":0,"ty":"sh","ix":1,"ks":{"a":1,"k":[{"i":{"x":0.833,"y":0.833},"o":{"x":0.167,"y":0.167},"t":48,"s":[{"i":[[0,0],[0,0],[0,0],[0,0]],"o":[[0,0],[0,0],[0,0],[0,0]],"v":[[83.897,12.657],[83.897,12.728],[-83.897,12.728],[-83.897,12.657]],"c":false}]},{"i":{"x":0.667,"y":1},"o":{"x":0.167,"y":0.167},"t":53.25,"s":[{"i":[[0,0],[0,0],[0,0],[0,0]],"o":[[0,0],[0,0],[0,0],[0,0]],"v":[[83.875,-12.847],[83.897,12.728],[-83.897,12.728],[-83.919,-12.847]],"c":false}]},{"i":{"x":0.667,"y":1},"o":{"x":0.333,"y":0},"t":67.25,"s":[{"i":[[0,0],[0,0],[0,0],[0,0]],"o":[[0,0],[0,0],[0,0],[0,0]],"v":[[83.897,-12.728],[83.897,12.728],[-83.897,12.728],[-83.897,-12.728]],"c":false}]},{"t":90,"s":[{"i":[[0,0],[0,0],[0,0],[0,0]],"o":[[0,0],[0,0],[0,0],[0,0]],"v":[[83.897,-12.728],[83.897,12.728],[-83.897,12.728],[-83.897,-12.728]],"c":false}]}],"ix":2},"nm":"Path 1","mn":"ADBE Vector Shape - Group","hd":false},{"ty":"st","c":{"a":0,"k":[0.031372550875,0.658823549747,0.541176497936,1],"ix":3,"x":"var $bm_rt;\n$bm_rt = comp('wired-outline-2077-hacking').layer('control').effect('secondary')('Color');"},"o":{"a":0,"k":100,"ix":4},"w":{"a":0,"k":12,"ix":5,"x":"var $bm_rt;\n$bm_rt = $bm_mul($bm_div(value, 2), comp('wired-outline-2077-hacking').layer('control').effect('stroke')('Menu'));"},"lc":2,"lj":2,"bm":0,"nm":".secondary","mn":"ADBE Vector Graphic - Stroke","hd":false,"cl":"secondary"},{"ty":"tr","p":{"a":0,"k":[249.872,411.179],"ix":2},"a":{"a":0,"k":[0,0],"ix":1},"s":{"a":0,"k":[100,100],"ix":3},"r":{"a":0,"k":0,"ix":6},"o":{"a":0,"k":100,"ix":7},"sk":{"a":0,"k":0,"ix":4},"sa":{"a":0,"k":0,"ix":5},"nm":"Transform"}],"nm":"Group 2","np":2,"cix":2,"bm":0,"ix":2,"mn":"ADBE Vector Group","hd":false},{"ty":"tr","p":{"a":0,"k":[249.872,411.179],"ix":2},"a":{"a":0,"k":[249.872,411.179],"ix":1},"s":{"a":0,"k":[100,100],"ix":3},"r":{"a":0,"k":0,"ix":6},"o":{"a":0,"k":100,"ix":7},"sk":{"a":0,"k":0,"ix":4},"sa":{"a":0,"k":0,"ix":5},"nm":"Transform"}],"nm":"Group 2","np":2,"cix":2,"bm":0,"ix":2,"mn":"ADBE Vector Group","hd":false}],"ip":48,"op":310,"st":10,"ct":1,"bm":0},{"ddd":0,"ind":2,"ty":4,"nm":"mask 2","td":1,"sr":1,"ks":{"o":{"a":0,"k":100,"ix":11},"r":{"a":0,"k":0,"ix":10},"p":{"a":1,"k":[{"i":{"x":0.501,"y":1},"o":{"x":0.167,"y":0.167},"t":48,"s":[215,392.892,0],"to":[0,0,0],"ti":[0,0,0]},{"i":{"x":0.667,"y":1},"o":{"x":0.333,"y":0},"t":63.75,"s":[215,372.892,0],"to":[0,0,0],"ti":[0,0,0]},{"t":90,"s":[215,387.892,0]}],"ix":2,"l":2},"a":{"a":1,"k":[{"i":{"x":0.833,"y":0.833},"o":{"x":0.167,"y":0.167},"t":48,"s":[250,422.854,0],"to":[0,0,0],"ti":[0,0,0]},{"i":{"x":0.833,"y":0.833},"o":{"x":0.167,"y":0.167},"t":67.25,"s":[250,422.854,0],"to":[0,0,0],"ti":[0,0,0]},{"t":90,"s":[250,422.854,0]}],"ix":1,"l":2},"s":{"a":1,"k":[{"i":{"x":[0.568,0.46,0.667],"y":[1,1,1]},"o":{"x":[0.167,0.167,0.167],"y":[0,0.167,0]},"t":48,"s":[100,100,100]},{"i":{"x":[0.667,0.667,0.667],"y":[1,1,1]},"o":{"x":[0.333,0.333,0.333],"y":[0,0,0]},"t":67.25,"s":[100,107,100]},{"t":90,"s":[100,100,100]}],"ix":6,"l":2}},"ao":0,"shapes":[{"ty":"gr","it":[{"ty":"gr","it":[{"ind":0,"ty":"sh","ix":1,"ks":{"a":1,"k":[{"i":{"x":0.833,"y":0.833},"o":{"x":0.167,"y":0.167},"t":48,"s":[{"i":[[0,0],[0,0],[0,0],[-6.901,0],[0,0],[0.411,-0.019]],"o":[[0,0],[0,0],[-0.411,-0.019],[0,0],[6.901,0],[0,0]],"v":[[84.025,85.673],[-84.025,85.673],[-84.542,85.621],[-72.576,85.586],[72.166,85.586],[84.133,85.621]],"c":true}]},{"i":{"x":0.667,"y":1},"o":{"x":0.167,"y":0.167},"t":53.25,"s":[{"i":[[0,0],[0,0],[0,0],[-6.901,0],[0,0],[0.411,-6.889]],"o":[[0,0],[0,0],[-0.411,-6.889],[0,0],[6.901,0],[0,0]],"v":[[84.025,60.287],[-84.025,60.287],[-84.542,41.828],[-72.576,29.127],[72.166,29.127],[84.133,41.828]],"c":true}]},{"i":{"x":0.667,"y":1},"o":{"x":0.333,"y":0},"t":67.25,"s":[{"i":[[0,0],[0,0],[0,0],[-6.901,0],[0,0],[0.411,-6.889]],"o":[[0,0],[0,0],[-0.411,-6.889],[0,0],[6.901,0],[0,0]],"v":[[84.025,60.287],[-84.025,60.287],[-90.462,-47.586],[-78.496,-60.287],[78.496,-60.287],[90.462,-47.586]],"c":true}]},{"t":90,"s":[{"i":[[0,0],[0,0],[0,0],[-6.901,0],[0,0],[0.411,-6.889]],"o":[[0,0],[0,0],[-0.411,-6.889],[0,0],[6.901,0],[0,0]],"v":[[84.025,60.287],[-84.025,60.287],[-90.462,-47.586],[-78.496,-60.287],[78.496,-60.287],[90.462,-47.586]],"c":true}]}],"ix":2},"nm":"Path 1","mn":"ADBE Vector Shape - Group","hd":false},{"ty":"tr","p":{"a":0,"k":[250,338.164],"ix":2},"a":{"a":0,"k":[0,0],"ix":1},"s":{"a":0,"k":[100,100],"ix":3},"r":{"a":0,"k":0,"ix":6},"o":{"a":0,"k":100,"ix":7},"sk":{"a":0,"k":0,"ix":4},"sa":{"a":0,"k":0,"ix":5},"nm":"Transform"}],"nm":"Group 1","np":1,"cix":2,"bm":0,"ix":1,"mn":"ADBE Vector Group","hd":false},{"ty":"gr","it":[{"ind":0,"ty":"sh","ix":1,"ks":{"a":1,"k":[{"i":{"x":0.833,"y":0.833},"o":{"x":0.167,"y":0.167},"t":48,"s":[{"i":[[0,0],[0,0],[0,0],[0,0]],"o":[[0,0],[0,0],[0,0],[0,0]],"v":[[83.897,12.657],[83.897,12.728],[-83.897,12.728],[-83.897,12.657]],"c":false}]},{"i":{"x":0.667,"y":1},"o":{"x":0.167,"y":0.167},"t":53.25,"s":[{"i":[[0,0],[0,0],[0,0],[0,0]],"o":[[0,0],[0,0],[0,0],[0,0]],"v":[[83.875,-12.847],[83.897,12.728],[-83.897,12.728],[-83.919,-12.847]],"c":false}]},{"i":{"x":0.667,"y":1},"o":{"x":0.333,"y":0},"t":67.25,"s":[{"i":[[0,0],[0,0],[0,0],[0,0]],"o":[[0,0],[0,0],[0,0],[0,0]],"v":[[83.897,-12.728],[83.897,12.728],[-83.897,12.728],[-83.897,-12.728]],"c":false}]},{"t":90,"s":[{"i":[[0,0],[0,0],[0,0],[0,0]],"o":[[0,0],[0,0],[0,0],[0,0]],"v":[[83.897,-12.728],[83.897,12.728],[-83.897,12.728],[-83.897,-12.728]],"c":false}]}],"ix":2},"nm":"Path 1","mn":"ADBE Vector Shape - Group","hd":false},{"ty":"tr","p":{"a":0,"k":[249.872,411.179],"ix":2},"a":{"a":0,"k":[0,0],"ix":1},"s":{"a":0,"k":[100,100],"ix":3},"r":{"a":0,"k":0,"ix":6},"o":{"a":0,"k":100,"ix":7},"sk":{"a":0,"k":0,"ix":4},"sa":{"a":0,"k":0,"ix":5},"nm":"Transform"}],"nm":"Group 2","np":1,"cix":2,"bm":0,"ix":2,"mn":"ADBE Vector Group","hd":false},{"ty":"tr","p":{"a":0,"k":[249.872,411.179],"ix":2},"a":{"a":0,"k":[249.872,411.179],"ix":1},"s":{"a":0,"k":[100,100],"ix":3},"r":{"a":0,"k":0,"ix":6},"o":{"a":0,"k":100,"ix":7},"sk":{"a":0,"k":0,"ix":4},"sa":{"a":0,"k":0,"ix":5},"nm":"Transform"}],"nm":"Group 2","np":2,"cix":2,"bm":0,"ix":1,"mn":"ADBE Vector Group","hd":false},{"ty":"fl","c":{"a":0,"k":[1,0,0,1],"ix":4},"o":{"a":0,"k":100,"ix":5},"r":1,"bm":0,"nm":"Fill 1","mn":"ADBE Vector Graphic - Fill","hd":false}],"ip":48,"op":310,"st":10,"ct":1,"bm":0},{"ddd":0,"ind":3,"ty":4,"nm":"head","tt":2,"tp":2,"sr":1,"ks":{"o":{"a":0,"k":100,"ix":11},"r":{"a":0,"k":0,"ix":10},"p":{"a":1,"k":[{"i":{"x":0.667,"y":1},"o":{"x":0.333,"y":0},"t":30,"s":[215,471.455,0],"to":[0,0,0],"ti":[0,0,0]},{"i":{"x":0.667,"y":1},"o":{"x":0.333,"y":0},"t":60,"s":[215,343.455,0],"to":[0,0,0],"ti":[0,0,0]},{"t":82,"s":[215,368.455,0]}],"ix":2,"l":2},"a":{"a":0,"k":[250,403.455,0],"ix":1,"l":2},"s":{"a":0,"k":[100,100,100],"ix":6,"l":2}},"ao":0,"shapes":[{"ty":"gr","it":[{"ind":0,"ty":"sh","ix":1,"ks":{"a":1,"k":[{"i":{"x":0.019,"y":1},"o":{"x":0.101,"y":0.103},"t":0,"s":[{"i":[[0,0],[-0.107,0.108],[0,0.229]],"o":[[0.032,-0.007],[0.155,-0.156],[0,0]],"v":[[-69.419,-26.38],[-68.999,-26.611],[-68.84,-27.208]],"c":false}]},{"i":{"x":0.833,"y":0.833},"o":{"x":0.333,"y":0},"t":30,"s":[{"i":[[0,0],[-13.911,14.042],[0,29.665]],"o":[[4.132,-0.855],[20.104,-20.294],[0,0]],"v":[[-68.03,64.732],[-13.613,34.835],[7.062,-42.684]],"c":false}]},{"i":{"x":0.833,"y":0.833},"o":{"x":0.167,"y":0.167},"t":37,"s":[{"i":[[0,0],[-10.848,14.536],[0,29.665]],"o":[[3.667,-1.05],[14.037,-18.811],[0,0]],"v":[[-61.141,61.774],[-13.785,34.973],[6.24,-28.766]],"c":false}]},{"i":{"x":0.667,"y":1},"o":{"x":0.167,"y":0.167},"t":42,"s":[{"i":[[0,0],[-8.764,11.67],[0,29.665]],"o":[[2.987,-1.335],[16.155,-20.767],[0,0]],"v":[[-38.066,57.357],[-13.57,35.35],[9.008,-36.431]],"c":false}]},{"i":{"x":0.667,"y":1},"o":{"x":0.333,"y":0},"t":64,"s":[{"i":[[0,0],[-1.943,2.286],[0,29.664]],"o":[[0.762,-2.268],[23.089,-27.173],[0,0]],"v":[[-18.077,43.279],[-12.863,36.585],[18.072,-61.529]],"c":false}]},{"t":82,"s":[{"i":[[0,0],[-1.349,2.68],[0,29.664]],"o":[[0.762,-2.268],[9.871,-19.566],[0,0]],"v":[[-18.077,43.279],[-14.863,35.835],[18.077,-43.279]],"c":false}]}],"ix":2},"nm":"Path 1","mn":"ADBE Vector Shape - Group","hd":false},{"ty":"st","c":{"a":0,"k":[0.070588238537,0.074509806931,0.192156866193,1],"ix":3,"x":"var $bm_rt;\n$bm_rt = comp('wired-outline-2077-hacking').layer('control').effect('primary')('Color');"},"o":{"a":0,"k":100,"ix":4},"w":{"a":0,"k":12,"ix":5,"x":"var $bm_rt;\n$bm_rt = $bm_mul($bm_div(value, 2), comp('wired-outline-2077-hacking').layer('control').effect('stroke')('Menu'));"},"lc":2,"lj":2,"bm":0,"nm":".primary","mn":"ADBE Vector Graphic - Stroke","hd":false,"cl":"primary"},{"ty":"tr","p":{"a":0,"k":[318.774,213.123],"ix":2},"a":{"a":0,"k":[0,0],"ix":1},"s":{"a":0,"k":[100,100],"ix":3},"r":{"a":0,"k":0,"ix":6},"o":{"a":0,"k":100,"ix":7},"sk":{"a":0,"k":0,"ix":4},"sa":{"a":0,"k":0,"ix":5},"nm":"Transform"}],"nm":"Group 1","np":2,"cix":2,"bm":0,"ix":1,"mn":"ADBE Vector Group","hd":false},{"ty":"gr","it":[{"ind":0,"ty":"sh","ix":1,"ks":{"a":1,"k":[{"i":{"x":0.019,"y":1},"o":{"x":0.101,"y":0.103},"t":0,"s":[{"i":[[0,0],[0.107,0.164],[0,0.229]],"o":[[-0.048,-0.006],[-0.121,-0.184],[0,0]],"v":[[68.162,-26.372],[67.747,-26.609],[67.57,-27.206]],"c":false}]},{"i":{"x":0.833,"y":0.833},"o":{"x":0.333,"y":0},"t":30,"s":[{"i":[[0,0],[13.948,21.292],[0,29.664]],"o":[[-6.195,-0.838],[-15.653,-23.895],[0,0]],"v":[[68.385,64.724],[14.617,33.844],[-8.37,-43.635]],"c":false}]},{"i":{"x":0.833,"y":0.833},"o":{"x":0.167,"y":0.167},"t":37,"s":[{"i":[[0,0],[10.901,14.471],[0,29.664]],"o":[[-5.444,-1.035],[-14.237,-18.899],[0,0]],"v":[[61.446,61.765],[14.652,34.119],[-7.203,-29.585]],"c":false}]},{"i":{"x":0.667,"y":1},"o":{"x":0.167,"y":0.167},"t":42,"s":[{"i":[[0,0],[8.802,11.623],[0,29.664]],"o":[[-4.347,-1.324],[-14.72,-19.022],[0,0]],"v":[[40.048,57.339],[14.176,34.815],[-9.747,-37.056]],"c":false}]},{"i":{"x":0.667,"y":1},"o":{"x":0.333,"y":0},"t":64,"s":[{"i":[[0,0],[1.929,2.298],[0,29.664]],"o":[[-0.753,-2.268],[-16.302,-19.423],[0,0]],"v":[[18.073,43.271],[12.617,37.094],[-18.078,-61.521]],"c":false}]},{"t":82,"s":[{"i":[[0,0],[1.349,2.68],[0,29.664]],"o":[[-0.753,-2.268],[-9.862,-19.566],[0,0]],"v":[[18.073,43.271],[14.867,35.844],[-18.073,-43.271]],"c":false}]}],"ix":2},"nm":"Path 1","mn":"ADBE Vector Shape - Group","hd":false},{"ty":"st","c":{"a":0,"k":[0.070588238537,0.074509806931,0.192156866193,1],"ix":3,"x":"var $bm_rt;\n$bm_rt = comp('wired-outline-2077-hacking').layer('control').effect('primary')('Color');"},"o":{"a":0,"k":100,"ix":4},"w":{"a":0,"k":12,"ix":5,"x":"var $bm_rt;\n$bm_rt = $bm_mul($bm_div(value, 2), comp('wired-outline-2077-hacking').layer('control').effect('stroke')('Menu'));"},"lc":2,"lj":2,"bm":0,"nm":".primary","mn":"ADBE Vector Graphic - Stroke","hd":false,"cl":"primary"},{"ty":"tr","p":{"a":0,"k":[181.184,213.114],"ix":2},"a":{"a":0,"k":[0,0],"ix":1},"s":{"a":0,"k":[100,100],"ix":3},"r":{"a":0,"k":0,"ix":6},"o":{"a":0,"k":100,"ix":7},"sk":{"a":0,"k":0,"ix":4},"sa":{"a":0,"k":0,"ix":5},"nm":"Transform"}],"nm":"Group 2","np":2,"cix":2,"bm":0,"ix":2,"mn":"ADBE Vector Group","hd":false},{"ty":"gr","it":[{"ind":0,"ty":"sh","ix":1,"ks":{"a":1,"k":[{"i":{"x":0.019,"y":1},"o":{"x":0.101,"y":0.103},"t":0,"s":[{"i":[[0.095,-0.051],[0.383,-0.177],[-0.151,0.135],[-0.129,0],[0,0],[-0.097,-0.086]],"o":[[-0.374,-0.177],[-0.092,-0.056],[0.097,-0.086],[0,0],[0.129,0],[0.151,0.135]],"v":[[-0.085,59.871],[-1.209,59.871],[-0.992,59.38],[-0.642,59.247],[-0.642,59.247],[-0.291,59.38]],"c":true}]},{"i":{"x":0.833,"y":0.833},"o":{"x":0.333,"y":0},"t":30,"s":[{"i":[[12.317,-6.665],[49.726,-22.987],[-19.662,17.47],[-16.761,0],[0,0],[-12.529,-11.133]],"o":[[-48.562,-22.987],[-12.004,-7.213],[12.529,-11.133],[0,0],[16.761,0],[19.662,17.47]],"v":[[72.152,49.107],[-73.756,49.116],[-45.564,-14.601],[-0.104,-31.887],[-0.104,-31.887],[45.357,-14.601]],"c":true}]},{"i":{"x":0.833,"y":0.833},"o":{"x":0.167,"y":0.167},"t":37,"s":[{"i":[[11.934,-6.665],[51.312,-12.89],[-19.662,17.47],[-16.761,0],[0,0],[-12.529,-11.133]],"o":[[-50.066,-10.632],[-11.631,-7.213],[12.529,-11.133],[0,0],[16.761,0],[19.662,17.47]],"v":[[71.576,63.077],[-72.802,63.084],[-45.557,-16.946],[-0.097,-34.231],[-0.097,-34.231],[45.364,-16.946]],"c":true}]},{"i":{"x":0.667,"y":1},"o":{"x":0.167,"y":0.167},"t":42,"s":[{"i":[[12.023,-6.665],[50.993,-10.287],[-20.155,17.47],[-17.182,0],[0,0],[-12.844,-11.133]],"o":[[-50.257,-9.531],[-11.718,-7.213],[12.844,-11.133],[0,0],[17.182,0],[20.155,17.47]],"v":[[74.517,55.487],[-75.483,55.493],[-46.701,-21.076],[-0.098,-38.362],[-0.098,-38.362],[46.504,-21.076]],"c":true}]},{"i":{"x":0.667,"y":1},"o":{"x":0.333,"y":0},"t":64,"s":[{"i":[[12.317,-6.665],[48.766,-33.183],[-21.773,17.47],[-18.56,0],[0,0],[-13.874,-11.133]],"o":[[-46.142,-33.183],[-12.004,-7.213],[13.874,-11.133],[0,0],[18.56,0],[21.773,17.47]],"v":[[84.146,30.637],[-84.261,30.637],[-50.445,-34.601],[-0.104,-51.887],[-0.104,-51.887],[50.237,-34.601]],"c":true}]},{"t":82,"s":[{"i":[[12.317,-6.665],[49.726,-22.987],[-19.662,17.47],[-16.761,0],[0,0],[-12.529,-11.133]],"o":[[-48.562,-22.987],[-12.004,-7.213],[12.529,-11.133],[0,0],[16.761,0],[19.662,17.47]],"v":[[84.152,48.887],[-84.256,48.887],[-45.512,-31.601],[-0.052,-48.887],[-0.052,-48.887],[45.408,-31.601]],"c":true}]}],"ix":2},"nm":"Path 1","mn":"ADBE Vector Shape - Group","hd":false},{"ty":"st","c":{"a":0,"k":[0.070588238537,0.074509806931,0.192156866193,1],"ix":3,"x":"var $bm_rt;\n$bm_rt = comp('wired-outline-2077-hacking').layer('control').effect('primary')('Color');"},"o":{"a":0,"k":100,"ix":4},"w":{"a":0,"k":12,"ix":5,"x":"var $bm_rt;\n$bm_rt = $bm_mul($bm_div(value, 2), comp('wired-outline-2077-hacking').layer('control').effect('stroke')('Menu'));"},"lc":2,"lj":2,"bm":0,"nm":".primary","mn":"ADBE Vector Graphic - Stroke","hd":false,"cl":"primary"},{"ty":"tr","p":{"a":0,"k":[249.99,126.081],"ix":2},"a":{"a":0,"k":[0,0],"ix":1},"s":{"a":0,"k":[100,100],"ix":3},"r":{"a":0,"k":0,"ix":6},"o":{"a":0,"k":100,"ix":7},"sk":{"a":0,"k":0,"ix":4},"sa":{"a":0,"k":0,"ix":5},"nm":"Transform"}],"nm":"Group 3","np":2,"cix":2,"bm":0,"ix":3,"mn":"ADBE Vector Group","hd":false},{"ty":"gr","it":[{"ind":0,"ty":"sh","ix":1,"ks":{"a":1,"k":[{"i":{"x":0.019,"y":1},"o":{"x":0.101,"y":0.103},"t":0,"s":[{"i":[[0,0],[0,0],[-0.072,-0.07],[-0.018,-0.012],[-0.085,0],[-0.065,0.045],[-0.005,0.132],[0,0]],"o":[[0,0],[0.004,0.108],[0.016,0.015],[0.065,0.045],[0.085,0],[0.101,-0.07],[0,0],[0,0]],"v":[[-1.007,-19.378],[-0.998,-19.157],[-0.875,-18.882],[-0.825,-18.84],[-0.596,-18.769],[-0.367,-18.84],[-0.194,-19.157],[-0.185,-19.369]],"c":false}]},{"i":{"x":0.833,"y":0.833},"o":{"x":0.333,"y":0},"t":30,"s":[{"i":[[0,0],[0,0],[-9.41,-9.09],[-2.34,-1.62],[-11,0],[-8.44,5.84],[-0.6,17.11],[0,0]],"o":[[0,0],[0.49,14.05],[2.05,1.98],[8.44,5.83],[11.01,0],[13.13,-9.08],[0,0],[0,0]],"v":[[-53.32,-37.82],[-52.175,-9.18],[-36.265,26.56],[-29.665,31.97],[-0.005,41.21],[29.675,31.96],[52.175,-9.18],[53.32,-36.71]],"c":false}]},{"i":{"x":0.833,"y":0.833},"o":{"x":0.167,"y":0.167},"t":37,"s":[{"i":[[0,0],[0,0],[-9.41,-9.09],[-2.34,-1.62],[-11,0],[-8.44,5.84],[-0.6,17.11],[0,0]],"o":[[0,0],[0.49,14.05],[2.05,1.98],[8.44,5.83],[11.01,0],[13.13,-9.08],[0,0],[0,0]],"v":[[-52.843,-18.893],[-52.175,-9.18],[-36.265,26.56],[-29.665,31.97],[-0.005,41.21],[29.675,31.96],[52.175,-9.18],[53.46,-18.206]],"c":false}]},{"i":{"x":0.667,"y":1},"o":{"x":0.167,"y":0.167},"t":42,"s":[{"i":[[0,0],[0,0],[-9.41,-9.09],[-2.34,-1.62],[-11,0],[-8.44,5.84],[-0.6,17.11],[0,0]],"o":[[0,0],[0.49,14.05],[2.05,1.98],[8.44,5.83],[11.01,0],[13.13,-9.08],[0,0],[0,0]],"v":[[-52.955,-26.229],[-52.175,-9.18],[-36.265,26.56],[-29.665,31.97],[-0.005,41.21],[29.675,31.96],[52.175,-9.18],[53.487,-25.852]],"c":false}]},{"i":{"x":0.667,"y":1},"o":{"x":0.333,"y":0},"t":64,"s":[{"i":[[0,0],[0,0],[-9.41,-9.09],[-2.34,-1.62],[-11,0],[-8.44,5.84],[-0.6,17.11],[0,0]],"o":[[0,0],[0.49,14.05],[2.05,1.98],[8.44,5.83],[11.01,0],[13.13,-9.08],[0,0],[0,0]],"v":[[-53.32,-63.07],[-52.175,-9.18],[-36.265,26.56],[-29.665,31.97],[-0.005,41.21],[29.675,31.96],[52.175,-9.18],[53.07,-63.71]],"c":false}]},{"t":82,"s":[{"i":[[0,0],[0,0],[-9.41,-9.09],[-2.34,-1.62],[-11,0],[-8.44,5.84],[-0.6,17.11],[0,0]],"o":[[0,0],[0.49,14.05],[2.05,1.98],[8.44,5.83],[11.01,0],[13.13,-9.08],[0,0],[0,0]],"v":[[-53.285,-41.07],[-52.175,-9.18],[-36.265,26.56],[-29.665,31.97],[-0.005,41.21],[29.675,31.96],[52.175,-9.18],[53.285,-41.21]],"c":false}]}],"ix":2},"nm":"Path 1","mn":"ADBE Vector Shape - Group","hd":false},{"ty":"st","c":{"a":0,"k":[0.070588238537,0.074509806931,0.192156866193,1],"ix":3,"x":"var $bm_rt;\n$bm_rt = comp('wired-outline-2077-hacking').layer('control').effect('primary')('Color');"},"o":{"a":0,"k":100,"ix":4},"w":{"a":0,"k":12,"ix":5,"x":"var $bm_rt;\n$bm_rt = $bm_mul($bm_div(value, 2), comp('wired-outline-2077-hacking').layer('control').effect('stroke')('Menu'));"},"lc":2,"lj":2,"bm":0,"nm":".primary","mn":"ADBE Vector Graphic - Stroke","hd":false,"cl":"primary"},{"ty":"tr","p":{"a":0,"k":[249.945,205.27],"ix":2},"a":{"a":0,"k":[0,0],"ix":1},"s":{"a":0,"k":[100,100],"ix":3},"r":{"a":0,"k":0,"ix":6},"o":{"a":0,"k":100,"ix":7},"sk":{"a":0,"k":0,"ix":4},"sa":{"a":0,"k":0,"ix":5},"nm":"Transform"}],"nm":"Group 4","np":2,"cix":2,"bm":0,"ix":4,"mn":"ADBE Vector Group","hd":false},{"ty":"gr","it":[{"ind":0,"ty":"sh","ix":1,"ks":{"a":1,"k":[{"i":{"x":0.019,"y":1},"o":{"x":0.101,"y":0.103},"t":0,"s":[{"i":[[0,0],[0,0],[0,0],[0,0.063],[0,0]],"o":[[0,0],[0,0.063],[0,0],[0,0],[0,0]],"v":[[-0.372,-71.125],[-0.372,-70.987],[-0.6,-70.812],[-0.829,-70.987],[-0.829,-71.125]],"c":false}]},{"i":{"x":0.667,"y":1},"o":{"x":0.333,"y":0},"t":30,"s":[{"i":[[0,0],[0,0],[0,0],[0,8.158],[0,0]],"o":[[0,0],[0,8.158],[0,0],[0,0],[0,0]],"v":[[29.669,-20.322],[29.669,-2.394],[-0.004,20.322],[-29.669,-2.394],[-29.669,-20.318]],"c":false}]},{"i":{"x":0.667,"y":1},"o":{"x":0.333,"y":0},"t":64,"s":[{"i":[[0,0],[0,0],[0,0],[0,8.158],[0,0]],"o":[[0,0],[0,8.158],[0,0],[0,0],[0,0]],"v":[[29.669,-20.322],[29.669,-2.394],[-0.004,20.322],[-29.669,-2.394],[-29.669,-20.318]],"c":false}]},{"t":82,"s":[{"i":[[0,0],[0,0],[0,0],[0,8.158],[0,0]],"o":[[0,0],[0,8.158],[0,0],[0,0],[0,0]],"v":[[29.669,-20.322],[29.669,-2.394],[-0.004,20.322],[-29.669,-2.394],[-29.669,-20.318]],"c":false}]}],"ix":2},"nm":"Path 1","mn":"ADBE Vector Shape - Group","hd":false},{"ty":"st","c":{"a":0,"k":[0.070588238537,0.074509806931,0.192156866193,1],"ix":3,"x":"var $bm_rt;\n$bm_rt = comp('wired-outline-2077-hacking').layer('control').effect('primary')('Color');"},"o":{"a":0,"k":100,"ix":4},"w":{"a":0,"k":12,"ix":5,"x":"var $bm_rt;\n$bm_rt = $bm_mul($bm_div(value, 2), comp('wired-outline-2077-hacking').layer('control').effect('stroke')('Menu'));"},"lc":2,"lj":2,"bm":0,"nm":".primary","mn":"ADBE Vector Graphic - Stroke","hd":false,"cl":"primary"},{"ty":"tr","p":{"a":0,"k":[249.949,257.554],"ix":2},"a":{"a":0,"k":[0,0],"ix":1},"s":{"a":0,"k":[100,100],"ix":3},"r":{"a":0,"k":0,"ix":6},"o":{"a":0,"k":100,"ix":7},"sk":{"a":0,"k":0,"ix":4},"sa":{"a":0,"k":0,"ix":5},"nm":"Transform"}],"nm":"Group 5","np":2,"cix":2,"bm":0,"ix":5,"mn":"ADBE Vector Group","hd":false}],"ip":1,"op":300,"st":0,"ct":1,"bm":0},{"ddd":0,"ind":4,"ty":4,"nm":"mask","td":1,"sr":1,"ks":{"o":{"a":0,"k":100,"ix":11},"r":{"a":0,"k":0,"ix":10},"p":{"a":1,"k":[{"i":{"x":0.501,"y":1},"o":{"x":0.167,"y":0.167},"t":48,"s":[215,392.892,0],"to":[0,0,0],"ti":[0,0,0]},{"i":{"x":0.667,"y":1},"o":{"x":0.333,"y":0},"t":63.75,"s":[215,372.892,0],"to":[0,0,0],"ti":[0,0,0]},{"t":90,"s":[215,387.892,0]}],"ix":2,"l":2},"a":{"a":1,"k":[{"i":{"x":0.833,"y":0.833},"o":{"x":0.167,"y":0.167},"t":48,"s":[250,422.854,0],"to":[0,0,0],"ti":[0,0,0]},{"i":{"x":0.833,"y":0.833},"o":{"x":0.167,"y":0.167},"t":67.25,"s":[250,422.854,0],"to":[0,0,0],"ti":[0,0,0]},{"t":90,"s":[250,422.854,0]}],"ix":1,"l":2},"s":{"a":1,"k":[{"i":{"x":[0.568,0.46,0.667],"y":[1,1,1]},"o":{"x":[0.167,0.167,0.167],"y":[0,0.167,0]},"t":48,"s":[100,100,100]},{"i":{"x":[0.667,0.667,0.667],"y":[1,1,1]},"o":{"x":[0.333,0.333,0.333],"y":[0,0,0]},"t":67.25,"s":[100,107,100]},{"t":90,"s":[100,100,100]}],"ix":6,"l":2}},"ao":0,"shapes":[{"ty":"gr","it":[{"ty":"gr","it":[{"ind":0,"ty":"sh","ix":1,"ks":{"a":1,"k":[{"i":{"x":0.833,"y":0.833},"o":{"x":0.167,"y":0.167},"t":48,"s":[{"i":[[0,0],[0,0],[0,0],[-6.901,0],[0,0],[0.411,-0.019]],"o":[[0,0],[0,0],[-0.411,-0.019],[0,0],[6.901,0],[0,0]],"v":[[84.025,85.673],[-84.025,85.673],[-84.542,85.621],[-72.576,85.586],[72.166,85.586],[84.133,85.621]],"c":true}]},{"i":{"x":0.667,"y":1},"o":{"x":0.167,"y":0.167},"t":53.25,"s":[{"i":[[0,0],[0,0],[0,0],[-6.901,0],[0,0],[0.411,-6.889]],"o":[[0,0],[0,0],[-0.411,-6.889],[0,0],[6.901,0],[0,0]],"v":[[84.025,60.287],[-84.025,60.287],[-84.542,41.828],[-72.576,29.127],[72.166,29.127],[84.133,41.828]],"c":true}]},{"i":{"x":0.667,"y":1},"o":{"x":0.333,"y":0},"t":67.25,"s":[{"i":[[0,0],[0,0],[0,0],[-6.901,0],[0,0],[0.411,-6.889]],"o":[[0,0],[0,0],[-0.411,-6.889],[0,0],[6.901,0],[0,0]],"v":[[84.025,60.287],[-84.025,60.287],[-90.462,-47.586],[-78.496,-60.287],[78.496,-60.287],[90.462,-47.586]],"c":true}]},{"t":90,"s":[{"i":[[0,0],[0,0],[0,0],[-6.901,0],[0,0],[0.411,-6.889]],"o":[[0,0],[0,0],[-0.411,-6.889],[0,0],[6.901,0],[0,0]],"v":[[84.025,60.287],[-84.025,60.287],[-90.462,-47.586],[-78.496,-60.287],[78.496,-60.287],[90.462,-47.586]],"c":true}]}],"ix":2},"nm":"Path 1","mn":"ADBE Vector Shape - Group","hd":false},{"ty":"tr","p":{"a":0,"k":[250,338.164],"ix":2},"a":{"a":0,"k":[0,0],"ix":1},"s":{"a":0,"k":[100,100],"ix":3},"r":{"a":0,"k":0,"ix":6},"o":{"a":0,"k":100,"ix":7},"sk":{"a":0,"k":0,"ix":4},"sa":{"a":0,"k":0,"ix":5},"nm":"Transform"}],"nm":"Group 1","np":1,"cix":2,"bm":0,"ix":1,"mn":"ADBE Vector Group","hd":false},{"ty":"gr","it":[{"ind":0,"ty":"sh","ix":1,"ks":{"a":1,"k":[{"i":{"x":0.833,"y":0.833},"o":{"x":0.167,"y":0.167},"t":48,"s":[{"i":[[0,0],[0,0],[0,0],[0,0]],"o":[[0,0],[0,0],[0,0],[0,0]],"v":[[83.897,12.657],[83.897,12.728],[-83.897,12.728],[-83.897,12.657]],"c":false}]},{"i":{"x":0.667,"y":1},"o":{"x":0.167,"y":0.167},"t":53.25,"s":[{"i":[[0,0],[0,0],[0,0],[0,0]],"o":[[0,0],[0,0],[0,0],[0,0]],"v":[[83.875,-12.847],[83.897,12.728],[-83.897,12.728],[-83.919,-12.847]],"c":false}]},{"i":{"x":0.667,"y":1},"o":{"x":0.333,"y":0},"t":67.25,"s":[{"i":[[0,0],[0,0],[0,0],[0,0]],"o":[[0,0],[0,0],[0,0],[0,0]],"v":[[83.897,-12.728],[83.897,12.728],[-83.897,12.728],[-83.897,-12.728]],"c":false}]},{"t":90,"s":[{"i":[[0,0],[0,0],[0,0],[0,0]],"o":[[0,0],[0,0],[0,0],[0,0]],"v":[[83.897,-12.728],[83.897,12.728],[-83.897,12.728],[-83.897,-12.728]],"c":false}]}],"ix":2},"nm":"Path 1","mn":"ADBE Vector Shape - Group","hd":false},{"ty":"tr","p":{"a":0,"k":[249.872,411.179],"ix":2},"a":{"a":0,"k":[0,0],"ix":1},"s":{"a":0,"k":[100,100],"ix":3},"r":{"a":0,"k":0,"ix":6},"o":{"a":0,"k":100,"ix":7},"sk":{"a":0,"k":0,"ix":4},"sa":{"a":0,"k":0,"ix":5},"nm":"Transform"}],"nm":"Group 2","np":1,"cix":2,"bm":0,"ix":2,"mn":"ADBE Vector Group","hd":false},{"ty":"tr","p":{"a":0,"k":[249.872,411.179],"ix":2},"a":{"a":0,"k":[249.872,411.179],"ix":1},"s":{"a":0,"k":[100,100],"ix":3},"r":{"a":0,"k":0,"ix":6},"o":{"a":0,"k":100,"ix":7},"sk":{"a":0,"k":0,"ix":4},"sa":{"a":0,"k":0,"ix":5},"nm":"Transform"}],"nm":"Group 2","np":2,"cix":2,"bm":0,"ix":1,"mn":"ADBE Vector Group","hd":false},{"ty":"fl","c":{"a":0,"k":[1,0,0,1],"ix":4},"o":{"a":0,"k":100,"ix":5},"r":1,"bm":0,"nm":"Fill 1","mn":"ADBE Vector Graphic - Fill","hd":false}],"ip":48,"op":310,"st":10,"ct":1,"bm":0},{"ddd":0,"ind":5,"ty":4,"nm":"body","tt":2,"tp":4,"sr":1,"ks":{"o":{"a":0,"k":100,"ix":11},"r":{"a":0,"k":0,"ix":10},"p":{"a":1,"k":[{"i":{"x":0.667,"y":1},"o":{"x":0.167,"y":0.167},"t":37,"s":[215,398.455,0],"to":[0,0,0],"ti":[0,0,0]},{"i":{"x":0.667,"y":1},"o":{"x":0.333,"y":0},"t":60,"s":[215,392.205,0],"to":[0,0,0],"ti":[0,0,0]},{"t":82,"s":[215,403.455,0]}],"ix":2,"l":2},"a":{"a":0,"k":[250,438.455,0],"ix":1,"l":2},"s":{"a":1,"k":[{"i":{"x":[0.667,0.667,0.667],"y":[1,1,1]},"o":{"x":[0.167,0.167,0.167],"y":[0,0.167,0]},"t":37,"s":[100,100,100]},{"i":{"x":[0.667,0.667,0.667],"y":[1,1,1]},"o":{"x":[0.333,0.333,0.333],"y":[0,0,0]},"t":60,"s":[100,107,100]},{"t":82,"s":[100,100,100]}],"ix":6,"l":2}},"ao":0,"shapes":[{"ty":"gr","it":[{"ind":0,"ty":"sh","ix":1,"ks":{"a":1,"k":[{"i":{"x":0.833,"y":0.833},"o":{"x":0.167,"y":0.167},"t":37,"s":[{"i":[[0,0],[-0.035,0],[0.069,-0.053],[0,0],[-0.084,-0.059],[0,0],[7.783,0],[17.701,0],[19.908,0],[0,0],[7.046,0],[0,0],[0.243,0.055],[0,0],[-106.271,0.001],[0,0],[-0.035,0]],"o":[[0.035,0],[93.063,0.002],[0,0],[0.105,0.056],[0,0],[-7.481,-0.001],[-18.047,0],[-17.596,0],[0,0],[-7.666,0],[0,0],[0.109,-0.073],[0,0],[0.026,-0.056],[0,0],[0.035,0],[0,0]],"v":[[0.324,43.589],[0.437,43.589],[118.931,43.636],[119.036,43.646],[118.834,43.639],[118.856,43.514],[51.842,43.694],[-0.117,43.694],[-51.908,43.694],[-52.084,43.694],[-118.859,43.653],[-118.859,43.653],[-118.759,43.647],[-119.026,43.636],[0.271,43.589],[0.279,43.589],[0.384,43.589]],"c":false}]},{"i":{"x":0.833,"y":0.833},"o":{"x":0.167,"y":0.167},"t":41,"s":[{"i":[[0,0],[-0.035,-0.007],[-3.531,-18.443],[0,0],[20.516,-0.519],[0,0],[7.783,-0.012],[17.701,0],[19.908,-0.103],[0,0],[7.046,0.039],[0,0],[0.243,20.321],[0,0],[-76.133,-0.635],[0,0],[-0.035,0]],"o":[[0.035,0],[67.913,-0.177],[0,0],[0.105,20.521],[0,0],[-7.481,-0.294],[-18.047,0.027],[-17.596,0],[0,0],[-7.666,0.16],[0,0],[-20.25,-1.27],[0,0],[1.826,-15.501],[0,0],[0.035,-0.007],[0,0]],"v":[[26.461,4.605],[26.537,4.594],[118.931,19.32],[119.036,22.902],[82.834,40.6],[81.456,40.661],[51.842,40.515],[-0.117,40.567],[-51.908,40.506],[-52.084,40.443],[-82.309,40.655],[-82.309,40.655],[-118.759,23.382],[-119.026,19.32],[-23.867,3.917],[-23.858,3.904],[-23.828,3.915]],"c":false}]},{"i":{"x":0.667,"y":1},"o":{"x":0.167,"y":0.167},"t":42,"s":[{"i":[[0,0],[-0.035,-0.009],[-4.431,-23.041],[0,0],[25.666,-0.635],[0,0],[7.783,-0.015],[17.701,0],[19.908,-0.128],[0,0],[7.046,0.049],[0,0],[0.243,25.387],[0,0],[-68.599,-0.794],[0,0],[-0.035,0]],"o":[[0.035,0],[61.625,-0.222],[0,0],[0.105,25.637],[0,0],[-7.481,-0.367],[-18.047,0.034],[-17.596,0],[0,0],[-7.666,0.2],[0,0],[-25.34,-1.569],[0,0],[2.276,-19.362],[0,0],[0.035,-0.009],[0,0]],"v":[[30.808,-1.227],[30.875,-1.24],[118.931,13.24],[119.036,17.715],[73.834,39.84],[72.106,39.947],[51.842,39.72],[-0.117,39.785],[-51.908,39.709],[-52.084,39.63],[-73.171,39.906],[-73.171,39.906],[-118.759,18.316],[-119.026,13.24],[-28.151,-1.65],[-28.143,-1.665],[-28.131,-1.652]],"c":false}]},{"i":{"x":0.667,"y":1},"o":{"x":0.167,"y":0},"t":60,"s":[{"i":[[0,0],[-0.035,-0.009],[0,-35.173],[0,0],[25.588,-1.592],[0,0],[6.455,-2.698],[17.701,0],[16.571,6.884],[0,0],[7.252,0.832],[0,0],[0.243,25.387],[0,0],[-33.229,6.709],[0,0],[-0.035,0]],"o":[[0.035,0],[33.185,6.726],[0,0],[0.105,25.637],[0,0],[-6.945,0.797],[-16.65,6.963],[-17.596,0],[0,0],[-6.735,-2.794],[0,0],[-25.34,-1.569],[0,0],[0,-35.2],[0,0],[0.035,-0.009],[0,0]],"v":[[50.696,-82.017],[50.81,-82],[118.92,-10.76],[119.036,17.716],[73.646,66.215],[71.918,66.322],[51.712,71.595],[-0.33,82.035],[-52.1,71.709],[-52.275,71.63],[-73.357,66.156],[-73.357,66.156],[-118.759,18.316],[-119.037,-10.76],[-50.857,-82.017],[-50.848,-82.017],[-50.743,-82.035]],"c":false}]},{"t":82,"s":[{"i":[[0,0],[-0.035,-0.009],[0,-35.173],[0,0],[25.588,-1.592],[0,0],[6.455,-2.698],[17.701,0],[16.571,6.884],[0,0],[7.252,0.832],[0,0],[0.243,25.387],[0,0],[-33.229,6.709],[0,0],[-0.035,0]],"o":[[0.035,0],[33.185,6.726],[0,0],[0.105,25.637],[0,0],[-6.945,0.797],[-16.65,6.963],[-17.596,0],[0,0],[-6.735,-2.794],[0,0],[-25.34,-1.569],[0,0],[0,-35.2],[0,0],[0.035,-0.009],[0,0]],"v":[[50.696,-82.017],[50.81,-82],[118.92,-10.76],[119.036,17.716],[73.646,66.215],[71.918,66.322],[51.712,71.595],[-0.33,82.035],[-52.1,71.709],[-52.275,71.63],[-73.357,66.156],[-73.357,66.156],[-118.759,18.316],[-119.037,-10.76],[-50.857,-82.017],[-50.848,-82.017],[-50.743,-82.035]],"c":false}]}],"ix":2},"nm":"Path 1","mn":"ADBE Vector Shape - Group","hd":false},{"ty":"st","c":{"a":0,"k":[0.070588238537,0.074509806931,0.192156866193,1],"ix":3,"x":"var $bm_rt;\n$bm_rt = comp('wired-outline-2077-hacking').layer('control').effect('primary')('Color');"},"o":{"a":0,"k":100,"ix":4},"w":{"a":0,"k":12,"ix":5,"x":"var $bm_rt;\n$bm_rt = $bm_mul($bm_div(value, 2), comp('wired-outline-2077-hacking').layer('control').effect('stroke')('Menu'));"},"lc":2,"lj":2,"bm":0,"nm":".primary","mn":"ADBE Vector Graphic - Stroke","hd":false,"cl":"primary"},{"ty":"tr","p":{"a":0,"k":[250,338.42],"ix":2},"a":{"a":0,"k":[0,0],"ix":1},"s":{"a":0,"k":[100,100],"ix":3},"r":{"a":0,"k":0,"ix":6},"o":{"a":0,"k":100,"ix":7},"sk":{"a":0,"k":0,"ix":4},"sa":{"a":0,"k":0,"ix":5},"nm":"Transform"}],"nm":"Group 6","np":2,"cix":2,"bm":0,"ix":1,"mn":"ADBE Vector Group","hd":false}],"ip":37,"op":337,"st":37,"ct":1,"bm":0}]},{"id":"comp_1","nm":"hover-pinch","fr":60,"layers":[{"ddd":0,"ind":1,"ty":4,"nm":"outline 3","sr":1,"ks":{"o":{"a":0,"k":100,"ix":11},"r":{"a":0,"k":0,"ix":10},"p":{"a":0,"k":[215,315.892,0],"ix":2,"l":2},"a":{"a":0,"k":[250,350.892,0],"ix":1,"l":2},"s":{"a":0,"k":[100,100,100],"ix":6,"l":2}},"ao":0,"shapes":[{"ty":"gr","it":[{"ind":0,"ty":"sh","ix":1,"ks":{"a":0,"k":{"i":[[0,-8.092],[8.092,0],[0,8.092],[-8.092,0]],"o":[[0,8.092],[-8.092,0],[0,-8.092],[8.092,0]],"v":[[14.652,0],[0,14.652],[-14.652,0],[0,-14.652]],"c":true},"ix":2},"nm":"Path 1","mn":"ADBE Vector Shape - Group","hd":false},{"ty":"st","c":{"a":0,"k":[0.031372550875,0.658823549747,0.541176497936,1],"ix":3,"x":"var $bm_rt;\n$bm_rt = comp('wired-outline-2077-hacking').layer('control').effect('secondary')('Color');"},"o":{"a":0,"k":100,"ix":4},"w":{"a":0,"k":12,"ix":5,"x":"var $bm_rt;\n$bm_rt = $bm_mul($bm_div(value, 2), comp('wired-outline-2077-hacking').layer('control').effect('stroke')('Menu'));"},"lc":2,"lj":2,"bm":0,"nm":".secondary","mn":"ADBE Vector Graphic - Stroke","hd":false,"cl":"secondary"},{"ty":"tr","p":{"a":0,"k":[250,332.698],"ix":2},"a":{"a":0,"k":[0,0],"ix":1},"s":{"a":0,"k":[100,100],"ix":3},"r":{"a":0,"k":0,"ix":6},"o":{"a":0,"k":100,"ix":7},"sk":{"a":0,"k":0,"ix":4},"sa":{"a":0,"k":0,"ix":5},"nm":"Transform"}],"nm":"Group 1","np":2,"cix":2,"bm":0,"ix":1,"mn":"ADBE Vector Group","hd":false},{"ty":"gr","it":[{"ty":"gr","it":[{"ind":0,"ty":"sh","ix":1,"ks":{"a":0,"k":{"i":[[0,0],[0,0],[0,0],[-6.901,0],[0,0],[0.411,-6.889]],"o":[[0,0],[0,0],[-0.411,-6.889],[0,0],[6.901,0],[0,0]],"v":[[84.025,60.287],[-84.025,60.287],[-90.462,-47.586],[-78.496,-60.287],[78.496,-60.287],[90.462,-47.586]],"c":true},"ix":2},"nm":"Path 1","mn":"ADBE Vector Shape - Group","hd":false},{"ty":"st","c":{"a":0,"k":[0.031372550875,0.658823549747,0.541176497936,1],"ix":3,"x":"var $bm_rt;\n$bm_rt = comp('wired-outline-2077-hacking').layer('control').effect('secondary')('Color');"},"o":{"a":0,"k":100,"ix":4},"w":{"a":0,"k":12,"ix":5,"x":"var $bm_rt;\n$bm_rt = $bm_mul($bm_div(value, 2), comp('wired-outline-2077-hacking').layer('control').effect('stroke')('Menu'));"},"lc":2,"lj":2,"bm":0,"nm":".secondary","mn":"ADBE Vector Graphic - Stroke","hd":false,"cl":"secondary"},{"ty":"tr","p":{"a":0,"k":[250,338.164],"ix":2},"a":{"a":0,"k":[0,0],"ix":1},"s":{"a":0,"k":[100,100],"ix":3},"r":{"a":0,"k":0,"ix":6},"o":{"a":0,"k":100,"ix":7},"sk":{"a":0,"k":0,"ix":4},"sa":{"a":0,"k":0,"ix":5},"nm":"Transform"}],"nm":"Group 1","np":2,"cix":2,"bm":0,"ix":1,"mn":"ADBE Vector Group","hd":false},{"ty":"gr","it":[{"ind":0,"ty":"sh","ix":1,"ks":{"a":0,"k":{"i":[[0,0],[0,0],[0,0],[0,0]],"o":[[0,0],[0,0],[0,0],[0,0]],"v":[[83.897,-12.728],[83.897,12.728],[-83.897,12.728],[-83.897,-12.728]],"c":false},"ix":2},"nm":"Path 1","mn":"ADBE Vector Shape - Group","hd":false},{"ty":"st","c":{"a":0,"k":[0.031372550875,0.658823549747,0.541176497936,1],"ix":3,"x":"var $bm_rt;\n$bm_rt = comp('wired-outline-2077-hacking').layer('control').effect('secondary')('Color');"},"o":{"a":0,"k":100,"ix":4},"w":{"a":0,"k":12,"ix":5,"x":"var $bm_rt;\n$bm_rt = $bm_mul($bm_div(value, 2), comp('wired-outline-2077-hacking').layer('control').effect('stroke')('Menu'));"},"lc":2,"lj":2,"bm":0,"nm":".secondary","mn":"ADBE Vector Graphic - Stroke","hd":false,"cl":"secondary"},{"ty":"tr","p":{"a":0,"k":[249.872,411.179],"ix":2},"a":{"a":0,"k":[0,0],"ix":1},"s":{"a":0,"k":[100,100],"ix":3},"r":{"a":0,"k":0,"ix":6},"o":{"a":0,"k":100,"ix":7},"sk":{"a":0,"k":0,"ix":4},"sa":{"a":0,"k":0,"ix":5},"nm":"Transform"}],"nm":"Group 2","np":2,"cix":2,"bm":0,"ix":2,"mn":"ADBE Vector Group","hd":false},{"ty":"tr","p":{"a":0,"k":[249.872,411.179],"ix":2},"a":{"a":0,"k":[249.872,411.179],"ix":1},"s":{"a":0,"k":[100,100],"ix":3},"r":{"a":0,"k":0,"ix":6},"o":{"a":0,"k":100,"ix":7},"sk":{"a":0,"k":0,"ix":4},"sa":{"a":0,"k":0,"ix":5},"nm":"Transform"}],"nm":"Group 2","np":2,"cix":2,"bm":0,"ix":2,"mn":"ADBE Vector Group","hd":false}],"ip":0,"op":300,"st":0,"ct":1,"bm":0},{"ddd":0,"ind":2,"ty":4,"nm":"mask","td":1,"sr":1,"ks":{"o":{"a":0,"k":100,"ix":11},"r":{"a":0,"k":0,"ix":10},"p":{"a":0,"k":[215,315.892,0],"ix":2,"l":2},"a":{"a":0,"k":[250,350.892,0],"ix":1,"l":2},"s":{"a":0,"k":[100,100,100],"ix":6,"l":2}},"ao":0,"shapes":[{"ty":"gr","it":[{"ty":"gr","it":[{"ind":0,"ty":"sh","ix":1,"ks":{"a":0,"k":{"i":[[0,0],[0,0],[0,0],[-6.901,0],[0,0],[0.411,-6.889]],"o":[[0,0],[0,0],[-0.411,-6.889],[0,0],[6.901,0],[0,0]],"v":[[84.025,60.287],[-84.025,60.287],[-90.462,-47.586],[-78.496,-60.287],[78.496,-60.287],[90.462,-47.586]],"c":true},"ix":2},"nm":"Path 1","mn":"ADBE Vector Shape - Group","hd":false},{"ty":"fl","c":{"a":0,"k":[1,1,1,1],"ix":4},"o":{"a":0,"k":100,"ix":5},"r":1,"bm":0,"nm":"Fill 1","mn":"ADBE Vector Graphic - Fill","hd":false},{"ty":"tr","p":{"a":0,"k":[250,338.164],"ix":2},"a":{"a":0,"k":[0,0],"ix":1},"s":{"a":0,"k":[100,100],"ix":3},"r":{"a":0,"k":0,"ix":6},"o":{"a":0,"k":100,"ix":7},"sk":{"a":0,"k":0,"ix":4},"sa":{"a":0,"k":0,"ix":5},"nm":"Transform"}],"nm":"Group 1","np":2,"cix":2,"bm":0,"ix":1,"mn":"ADBE Vector Group","hd":false},{"ty":"gr","it":[{"ind":0,"ty":"sh","ix":1,"ks":{"a":0,"k":{"i":[[0,0],[0,0],[0,0],[0,0]],"o":[[0,0],[0,0],[0,0],[0,0]],"v":[[83.897,-12.728],[83.897,12.728],[-83.897,12.728],[-83.897,-12.728]],"c":false},"ix":2},"nm":"Path 1","mn":"ADBE Vector Shape - Group","hd":false},{"ty":"fl","c":{"a":0,"k":[1,1,1,1],"ix":4},"o":{"a":0,"k":100,"ix":5},"r":1,"bm":0,"nm":"Fill 1","mn":"ADBE Vector Graphic - Fill","hd":false},{"ty":"tr","p":{"a":0,"k":[249.872,411.179],"ix":2},"a":{"a":0,"k":[0,0],"ix":1},"s":{"a":0,"k":[100,100],"ix":3},"r":{"a":0,"k":0,"ix":6},"o":{"a":0,"k":100,"ix":7},"sk":{"a":0,"k":0,"ix":4},"sa":{"a":0,"k":0,"ix":5},"nm":"Transform"}],"nm":"Group 2","np":2,"cix":2,"bm":0,"ix":2,"mn":"ADBE Vector Group","hd":false},{"ty":"tr","p":{"a":0,"k":[249.872,411.179],"ix":2},"a":{"a":0,"k":[249.872,411.179],"ix":1},"s":{"a":0,"k":[100,100],"ix":3},"r":{"a":0,"k":0,"ix":6},"o":{"a":0,"k":100,"ix":7},"sk":{"a":0,"k":0,"ix":4},"sa":{"a":0,"k":0,"ix":5},"nm":"Transform"}],"nm":"Group 2","np":2,"cix":2,"bm":0,"ix":1,"mn":"ADBE Vector Group","hd":false}],"ip":0,"op":300,"st":0,"ct":1,"bm":0},{"ddd":0,"ind":3,"ty":4,"nm":"outline","tt":2,"tp":2,"sr":1,"ks":{"o":{"a":0,"k":100,"ix":11},"r":{"a":0,"k":0,"ix":10},"p":{"a":0,"k":[215,368.455,0],"ix":2,"l":2},"a":{"a":0,"k":[250,403.455,0],"ix":1,"l":2},"s":{"a":1,"k":[{"i":{"x":[0.667,0.667,0.667],"y":[1,1,1]},"o":{"x":[0.333,0.333,0.333],"y":[0,0,0]},"t":0,"s":[100,100,100]},{"i":{"x":[0.667,0.667,0.667],"y":[1,1,1]},"o":{"x":[0.333,0.333,0.333],"y":[0,0,0]},"t":8,"s":[98,102,100]},{"i":{"x":[0.667,0.667,0.667],"y":[1,1,1]},"o":{"x":[0.333,0.333,0.333],"y":[0,0,0]},"t":30,"s":[102,98,100]},{"i":{"x":[0.667,0.667,0.667],"y":[1,1,1]},"o":{"x":[0.333,0.333,0.333],"y":[0,0,0]},"t":45,"s":[100,100,100]},{"i":{"x":[0.667,0.667,0.667],"y":[1,1,1]},"o":{"x":[0.333,0.333,0.333],"y":[0,0,0]},"t":52,"s":[101,99,100]},{"i":{"x":[0.667,0.667,0.667],"y":[1,1,1]},"o":{"x":[0.333,0.333,0.333],"y":[0,0,0]},"t":59,"s":[100,100,100]},{"i":{"x":[0.667,0.667,0.667],"y":[1,1,1]},"o":{"x":[0.333,0.333,0.333],"y":[0,0,0]},"t":66,"s":[101,99,100]},{"i":{"x":[0.667,0.667,0.667],"y":[1,1,1]},"o":{"x":[0.333,0.333,0.333],"y":[0,0,0]},"t":74,"s":[100,100,100]},{"i":{"x":[0.667,0.667,0.667],"y":[1,1,1]},"o":{"x":[0.333,0.333,0.333],"y":[0,0,0]},"t":90,"s":[102,98,100]},{"i":{"x":[0.667,0.667,0.667],"y":[1,1,1]},"o":{"x":[0.333,0.333,0.333],"y":[0,0,0]},"t":110.93,"s":[98,102,100]},{"t":120,"s":[100,100,100]}],"ix":6,"l":2}},"ao":0,"shapes":[{"ty":"gr","it":[{"ind":0,"ty":"sh","ix":1,"ks":{"a":1,"k":[{"i":{"x":0.667,"y":1},"o":{"x":0.333,"y":0},"t":0,"s":[{"i":[[0,0],[-1.349,2.68],[0,29.664]],"o":[[0.762,-2.268],[9.871,-19.566],[0,0]],"v":[[-18.077,43.279],[-14.863,35.835],[18.077,-43.279]],"c":false}]},{"i":{"x":0.667,"y":1},"o":{"x":0.333,"y":0},"t":30,"s":[{"i":[[0,0],[-2.099,2.017],[-5.101,20.377]],"o":[[0.762,-2.134],[17.589,-16.896],[0,0]],"v":[[-18.077,52.975],[-12.863,48.087],[19.077,7.521]],"c":false}]},{"i":{"x":0.667,"y":1},"o":{"x":0.333,"y":0},"t":90,"s":[{"i":[[0,0],[-2.099,2.017],[-5.101,20.377]],"o":[[0.762,-2.134],[17.589,-16.896],[0,0]],"v":[[-18.077,52.975],[-12.863,48.087],[19.077,7.521]],"c":false}]},{"t":110.9296875,"s":[{"i":[[0,0],[-1.349,2.68],[0,29.664]],"o":[[0.762,-2.268],[9.871,-19.566],[0,0]],"v":[[-18.077,43.279],[-14.863,35.835],[18.077,-43.279]],"c":false}]}],"ix":2},"nm":"Path 1","mn":"ADBE Vector Shape - Group","hd":false},{"ty":"st","c":{"a":0,"k":[0.070588238537,0.074509806931,0.192156866193,1],"ix":3,"x":"var $bm_rt;\n$bm_rt = comp('wired-outline-2077-hacking').layer('control').effect('primary')('Color');"},"o":{"a":0,"k":100,"ix":4},"w":{"a":0,"k":12,"ix":5,"x":"var $bm_rt;\n$bm_rt = $bm_mul($bm_div(value, 2), comp('wired-outline-2077-hacking').layer('control').effect('stroke')('Menu'));"},"lc":2,"lj":2,"bm":0,"nm":".primary","mn":"ADBE Vector Graphic - Stroke","hd":false,"cl":"primary"},{"ty":"tr","p":{"a":0,"k":[318.774,213.123],"ix":2},"a":{"a":0,"k":[0,0],"ix":1},"s":{"a":0,"k":[100,100],"ix":3},"r":{"a":0,"k":0,"ix":6},"o":{"a":0,"k":100,"ix":7},"sk":{"a":0,"k":0,"ix":4},"sa":{"a":0,"k":0,"ix":5},"nm":"Transform"}],"nm":"Group 1","np":2,"cix":2,"bm":0,"ix":1,"mn":"ADBE Vector Group","hd":false},{"ty":"gr","it":[{"ind":0,"ty":"sh","ix":1,"ks":{"a":1,"k":[{"i":{"x":0.667,"y":1},"o":{"x":0.333,"y":0},"t":0,"s":[{"i":[[0,0],[1.349,2.68],[0,29.664]],"o":[[-0.753,-2.268],[-9.862,-19.566],[0,0]],"v":[[18.073,43.271],[14.867,35.844],[-18.073,-43.271]],"c":false}]},{"i":{"x":0.667,"y":1},"o":{"x":0.333,"y":0},"t":30,"s":[{"i":[[0,0],[2.627,1.364],[2.138,10.967]],"o":[[-0.753,-2.134],[-20.302,-10.545],[0,0]],"v":[[18.073,52.967],[12.117,49.978],[-17.073,20.467]],"c":false}]},{"i":{"x":0.667,"y":1},"o":{"x":0.333,"y":0},"t":90,"s":[{"i":[[0,0],[2.627,1.364],[2.138,10.967]],"o":[[-0.753,-2.134],[-20.302,-10.545],[0,0]],"v":[[18.073,52.967],[12.117,49.978],[-17.073,20.467]],"c":false}]},{"t":110.9296875,"s":[{"i":[[0,0],[1.349,2.68],[0,29.664]],"o":[[-0.753,-2.268],[-9.862,-19.566],[0,0]],"v":[[18.073,43.271],[14.867,35.844],[-18.073,-43.271]],"c":false}]}],"ix":2},"nm":"Path 1","mn":"ADBE Vector Shape - Group","hd":false},{"ty":"st","c":{"a":0,"k":[0.070588238537,0.074509806931,0.192156866193,1],"ix":3,"x":"var $bm_rt;\n$bm_rt = comp('wired-outline-2077-hacking').layer('control').effect('primary')('Color');"},"o":{"a":0,"k":100,"ix":4},"w":{"a":0,"k":12,"ix":5,"x":"var $bm_rt;\n$bm_rt = $bm_mul($bm_div(value, 2), comp('wired-outline-2077-hacking').layer('control').effect('stroke')('Menu'));"},"lc":2,"lj":2,"bm":0,"nm":".primary","mn":"ADBE Vector Graphic - Stroke","hd":false,"cl":"primary"},{"ty":"tr","p":{"a":0,"k":[181.184,213.114],"ix":2},"a":{"a":0,"k":[0,0],"ix":1},"s":{"a":0,"k":[100,100],"ix":3},"r":{"a":0,"k":0,"ix":6},"o":{"a":0,"k":100,"ix":7},"sk":{"a":0,"k":0,"ix":4},"sa":{"a":0,"k":0,"ix":5},"nm":"Transform"}],"nm":"Group 2","np":2,"cix":2,"bm":0,"ix":2,"mn":"ADBE Vector Group","hd":false},{"ty":"gr","it":[{"ind":0,"ty":"sh","ix":1,"ks":{"a":1,"k":[{"i":{"x":0.667,"y":1},"o":{"x":0.333,"y":0},"t":0,"s":[{"i":[[12.317,-6.665],[49.726,-22.987],[-19.662,17.47],[-16.761,0],[0,0],[-12.529,-11.133]],"o":[[-48.562,-22.987],[-12.004,-7.213],[12.529,-11.133],[0,0],[16.761,0],[19.662,17.47]],"v":[[84.152,48.887],[-84.256,48.887],[-45.512,-31.601],[-0.052,-48.887],[-0.052,-48.887],[45.408,-31.601]],"c":true}]},{"i":{"x":0.667,"y":1},"o":{"x":0.333,"y":0},"t":30,"s":[{"i":[[15.903,-37.364],[4.81,-38.669],[-19.662,14.1],[-16.761,0],[0,0],[-12.529,-8.985]],"o":[[-0.347,-15.96],[-11.44,-43.367],[12.529,-8.985],[0,0],[16.761,0],[19.662,14.1]],"v":[[83.857,107.682],[-85.55,107.16],[-45.512,-2.13],[-0.052,-16.081],[-0.052,-16.081],[45.408,-2.13]],"c":true}]},{"i":{"x":0.667,"y":1},"o":{"x":0.333,"y":0},"t":90,"s":[{"i":[[15.903,-37.364],[4.81,-38.669],[-19.662,14.1],[-16.761,0],[0,0],[-12.529,-8.985]],"o":[[-0.347,-15.96],[-11.44,-43.367],[12.529,-8.985],[0,0],[16.761,0],[19.662,14.1]],"v":[[83.857,107.682],[-85.55,107.16],[-45.512,-2.13],[-0.052,-16.081],[-0.052,-16.081],[45.408,-2.13]],"c":true}]},{"t":110.9296875,"s":[{"i":[[12.317,-6.665],[49.726,-22.987],[-19.662,17.47],[-16.761,0],[0,0],[-12.529,-11.133]],"o":[[-48.562,-22.987],[-12.004,-7.213],[12.529,-11.133],[0,0],[16.761,0],[19.662,17.47]],"v":[[84.152,48.887],[-84.256,48.887],[-45.512,-31.601],[-0.052,-48.887],[-0.052,-48.887],[45.408,-31.601]],"c":true}]}],"ix":2},"nm":"Path 1","mn":"ADBE Vector Shape - Group","hd":false},{"ty":"st","c":{"a":0,"k":[0.070588238537,0.074509806931,0.192156866193,1],"ix":3,"x":"var $bm_rt;\n$bm_rt = comp('wired-outline-2077-hacking').layer('control').effect('primary')('Color');"},"o":{"a":0,"k":100,"ix":4},"w":{"a":0,"k":12,"ix":5,"x":"var $bm_rt;\n$bm_rt = $bm_mul($bm_div(value, 2), comp('wired-outline-2077-hacking').layer('control').effect('stroke')('Menu'));"},"lc":2,"lj":2,"bm":0,"nm":".primary","mn":"ADBE Vector Graphic - Stroke","hd":false,"cl":"primary"},{"ty":"tr","p":{"a":0,"k":[249.99,126.081],"ix":2},"a":{"a":0,"k":[0,0],"ix":1},"s":{"a":0,"k":[100,100],"ix":3},"r":{"a":0,"k":0,"ix":6},"o":{"a":0,"k":100,"ix":7},"sk":{"a":0,"k":0,"ix":4},"sa":{"a":0,"k":0,"ix":5},"nm":"Transform"}],"nm":"Group 3","np":2,"cix":2,"bm":0,"ix":3,"mn":"ADBE Vector Group","hd":false},{"ty":"gr","it":[{"ind":0,"ty":"sh","ix":1,"ks":{"a":1,"k":[{"i":{"x":0.667,"y":1},"o":{"x":0.333,"y":0},"t":0,"s":[{"i":[[0,0],[0,0],[-9.41,-9.09],[-2.34,-1.62],[-11,0],[-8.44,5.84],[-0.6,17.11],[0,0]],"o":[[0,0],[0.49,14.05],[2.05,1.98],[8.44,5.83],[11.01,0],[13.13,-9.08],[0,0],[0,0]],"v":[[-53.285,-41.07],[-52.175,-9.18],[-36.265,26.56],[-29.665,31.97],[-0.005,41.21],[29.675,31.96],[52.175,-9.18],[53.285,-41.21]],"c":false}]},{"i":{"x":0.667,"y":1},"o":{"x":0.333,"y":0},"t":30,"s":[{"i":[[0,0],[0,0],[-9.411,-8.552],[-2.342,-1.522],[-11,0],[-8.441,5.493],[-0.6,16.099],[0,0]],"o":[[0,0],[0.49,13.22],[2.05,1.863],[8.44,5.485],[11.01,0],[13.13,-8.543],[0,0],[0,0]],"v":[[-54.3,11.005],[-52,21.486],[-36.09,55.114],[-29.49,60.204],[0.17,68.898],[29.85,60.195],[52.35,21.486],[52.52,17.695]],"c":false}]},{"i":{"x":0.667,"y":1},"o":{"x":0.333,"y":0},"t":90,"s":[{"i":[[0,0],[0,0],[-9.411,-8.552],[-2.342,-1.522],[-11,0],[-8.441,5.493],[-0.6,16.099],[0,0]],"o":[[0,0],[0.49,13.22],[2.05,1.863],[8.44,5.485],[11.01,0],[13.13,-8.543],[0,0],[0,0]],"v":[[-54.3,11.005],[-52,21.486],[-36.09,55.114],[-29.49,60.204],[0.17,68.898],[29.85,60.195],[52.35,21.486],[52.52,17.695]],"c":false}]},{"t":110.9296875,"s":[{"i":[[0,0],[0,0],[-9.41,-9.09],[-2.34,-1.62],[-11,0],[-8.44,5.84],[-0.6,17.11],[0,0]],"o":[[0,0],[0.49,14.05],[2.05,1.98],[8.44,5.83],[11.01,0],[13.13,-9.08],[0,0],[0,0]],"v":[[-53.285,-41.07],[-52.175,-9.18],[-36.265,26.56],[-29.665,31.97],[-0.005,41.21],[29.675,31.96],[52.175,-9.18],[53.285,-41.21]],"c":false}]}],"ix":2},"nm":"Path 1","mn":"ADBE Vector Shape - Group","hd":false},{"ty":"st","c":{"a":0,"k":[0.070588238537,0.074509806931,0.192156866193,1],"ix":3,"x":"var $bm_rt;\n$bm_rt = comp('wired-outline-2077-hacking').layer('control').effect('primary')('Color');"},"o":{"a":0,"k":100,"ix":4},"w":{"a":0,"k":12,"ix":5,"x":"var $bm_rt;\n$bm_rt = $bm_mul($bm_div(value, 2), comp('wired-outline-2077-hacking').layer('control').effect('stroke')('Menu'));"},"lc":2,"lj":2,"bm":0,"nm":".primary","mn":"ADBE Vector Graphic - Stroke","hd":false,"cl":"primary"},{"ty":"tr","p":{"a":0,"k":[249.945,205.27],"ix":2},"a":{"a":0,"k":[0,0],"ix":1},"s":{"a":0,"k":[100,100],"ix":3},"r":{"a":0,"k":0,"ix":6},"o":{"a":0,"k":100,"ix":7},"sk":{"a":0,"k":0,"ix":4},"sa":{"a":0,"k":0,"ix":5},"nm":"Transform"}],"nm":"Group 4","np":2,"cix":2,"bm":0,"ix":4,"mn":"ADBE Vector Group","hd":false},{"ty":"gr","it":[{"ind":0,"ty":"sh","ix":1,"ks":{"a":1,"k":[{"i":{"x":0.667,"y":1},"o":{"x":0.333,"y":0},"t":0,"s":[{"i":[[0,0],[0,0],[0,0],[0,8.158],[0,0]],"o":[[0,0],[0,8.158],[0,0],[0,0],[0,0]],"v":[[29.669,-20.322],[29.669,-2.394],[-0.004,20.322],[-29.669,-2.394],[-29.669,-20.318]],"c":false}]},{"i":{"x":0.667,"y":1},"o":{"x":0.333,"y":0},"t":30,"s":[{"i":[[0,0],[0,0],[0,0],[0,7.676],[0,0]],"o":[[0,0],[0,7.676],[0,0],[0,0],[0,0]],"v":[[29.844,7.913],[29.669,7.375],[-0.004,28.748],[-29.669,7.375],[-29.494,7.917]],"c":false}]},{"i":{"x":0.667,"y":1},"o":{"x":0.333,"y":0},"t":90,"s":[{"i":[[0,0],[0,0],[0,0],[0,7.676],[0,0]],"o":[[0,0],[0,7.676],[0,0],[0,0],[0,0]],"v":[[29.844,7.913],[29.669,7.375],[-0.004,28.748],[-29.669,7.375],[-29.494,7.917]],"c":false}]},{"t":110.9296875,"s":[{"i":[[0,0],[0,0],[0,0],[0,8.158],[0,0]],"o":[[0,0],[0,8.158],[0,0],[0,0],[0,0]],"v":[[29.669,-20.322],[29.669,-2.394],[-0.004,20.322],[-29.669,-2.394],[-29.669,-20.318]],"c":false}]}],"ix":2},"nm":"Path 1","mn":"ADBE Vector Shape - Group","hd":false},{"ty":"st","c":{"a":0,"k":[0.070588238537,0.074509806931,0.192156866193,1],"ix":3,"x":"var $bm_rt;\n$bm_rt = comp('wired-outline-2077-hacking').layer('control').effect('primary')('Color');"},"o":{"a":0,"k":100,"ix":4},"w":{"a":0,"k":12,"ix":5,"x":"var $bm_rt;\n$bm_rt = $bm_mul($bm_div(value, 2), comp('wired-outline-2077-hacking').layer('control').effect('stroke')('Menu'));"},"lc":2,"lj":2,"bm":0,"nm":".primary","mn":"ADBE Vector Graphic - Stroke","hd":false,"cl":"primary"},{"ty":"tr","p":{"a":0,"k":[249.949,257.554],"ix":2},"a":{"a":0,"k":[0,0],"ix":1},"s":{"a":0,"k":[100,100],"ix":3},"r":{"a":0,"k":0,"ix":6},"o":{"a":0,"k":100,"ix":7},"sk":{"a":0,"k":0,"ix":4},"sa":{"a":0,"k":0,"ix":5},"nm":"Transform"}],"nm":"Group 5","np":2,"cix":2,"bm":0,"ix":5,"mn":"ADBE Vector Group","hd":false},{"ty":"gr","it":[{"ind":0,"ty":"sh","ix":1,"ks":{"a":1,"k":[{"i":{"x":0.667,"y":1},"o":{"x":0.333,"y":0},"t":0,"s":[{"i":[[0,0],[-0.035,-0.009],[0,-35.173],[0,0],[25.588,-1.592],[0,0],[6.455,-2.698],[17.701,0],[16.571,6.884],[0,0],[7.252,0.832],[0,0],[0.243,25.387],[0,0],[-33.229,6.709],[0,0],[-0.035,0]],"o":[[0.035,0],[33.185,6.726],[0,0],[0.105,25.637],[0,0],[-6.945,0.797],[-16.65,6.963],[-17.596,0],[0,0],[-6.735,-2.794],[0,0],[-25.34,-1.569],[0,0],[0,-35.2],[0,0],[0.035,-0.009],[0,0]],"v":[[50.696,-82.017],[50.81,-82],[118.92,-10.76],[119.036,17.716],[73.646,66.215],[71.918,66.322],[51.712,71.595],[-0.33,82.035],[-52.1,71.709],[-52.275,71.63],[-73.357,66.156],[-73.357,66.156],[-118.759,18.316],[-119.037,-10.76],[-50.857,-82.017],[-50.848,-82.017],[-50.743,-82.035]],"c":false}]},{"i":{"x":0.667,"y":1},"o":{"x":0.333,"y":0},"t":30,"s":[{"i":[[0,0],[-0.035,-0.008],[0,-33.095],[0,0],[25.588,-1.498],[0,0],[6.454,-2.54],[17.701,0],[16.571,6.477],[0,0],[7.252,0.783],[0,0],[0.243,23.887],[0,0],[-33.229,6.312],[0,0],[-0.035,0]],"o":[[0.035,0],[33.185,6.329],[0,0],[0.105,24.122],[0,0],[-6.945,0.75],[-16.65,6.551],[-17.596,0],[0,0],[-6.735,-2.629],[0,0],[-25.34,-1.477],[0,0],[0,-33.119],[0,0],[0.035,-0.008],[0,0]],"v":[[50.696,-72.322],[50.81,-72.306],[118.92,-5.275],[119.036,21.517],[73.646,67.15],[71.918,67.251],[51.712,72.212],[-0.33,82.035],[-52.1,72.319],[-52.275,72.245],[-73.357,67.094],[-73.357,67.094],[-118.759,22.082],[-119.037,-5.275],[-50.857,-72.322],[-50.848,-72.322],[-50.743,-72.339]],"c":false}]},{"i":{"x":0.667,"y":1},"o":{"x":0.333,"y":0},"t":90,"s":[{"i":[[0,0],[-0.035,-0.008],[0,-33.095],[0,0],[25.588,-1.498],[0,0],[6.454,-2.54],[17.701,0],[16.571,6.477],[0,0],[7.252,0.783],[0,0],[0.243,23.887],[0,0],[-33.229,6.312],[0,0],[-0.035,0]],"o":[[0.035,0],[33.185,6.329],[0,0],[0.105,24.122],[0,0],[-6.945,0.75],[-16.65,6.551],[-17.596,0],[0,0],[-6.735,-2.629],[0,0],[-25.34,-1.477],[0,0],[0,-33.119],[0,0],[0.035,-0.008],[0,0]],"v":[[50.696,-72.322],[50.81,-72.306],[118.92,-5.275],[119.036,21.517],[73.646,67.15],[71.918,67.251],[51.712,72.212],[-0.33,82.035],[-52.1,72.319],[-52.275,72.245],[-73.357,67.094],[-73.357,67.094],[-118.759,22.082],[-119.037,-5.275],[-50.857,-72.322],[-50.848,-72.322],[-50.743,-72.339]],"c":false}]},{"t":110.9296875,"s":[{"i":[[0,0],[-0.035,-0.009],[0,-35.173],[0,0],[25.588,-1.592],[0,0],[6.455,-2.698],[17.701,0],[16.571,6.884],[0,0],[7.252,0.832],[0,0],[0.243,25.387],[0,0],[-33.229,6.709],[0,0],[-0.035,0]],"o":[[0.035,0],[33.185,6.726],[0,0],[0.105,25.637],[0,0],[-6.945,0.797],[-16.65,6.963],[-17.596,0],[0,0],[-6.735,-2.794],[0,0],[-25.34,-1.569],[0,0],[0,-35.2],[0,0],[0.035,-0.009],[0,0]],"v":[[50.696,-82.017],[50.81,-82],[118.92,-10.76],[119.036,17.716],[73.646,66.215],[71.918,66.322],[51.712,71.595],[-0.33,82.035],[-52.1,71.709],[-52.275,71.63],[-73.357,66.156],[-73.357,66.156],[-118.759,18.316],[-119.037,-10.76],[-50.857,-82.017],[-50.848,-82.017],[-50.743,-82.035]],"c":false}]}],"ix":2},"nm":"Path 1","mn":"ADBE Vector Shape - Group","hd":false},{"ty":"st","c":{"a":0,"k":[0.070588238537,0.074509806931,0.192156866193,1],"ix":3,"x":"var $bm_rt;\n$bm_rt = comp('wired-outline-2077-hacking').layer('control').effect('primary')('Color');"},"o":{"a":0,"k":100,"ix":4},"w":{"a":0,"k":12,"ix":5,"x":"var $bm_rt;\n$bm_rt = $bm_mul($bm_div(value, 2), comp('wired-outline-2077-hacking').layer('control').effect('stroke')('Menu'));"},"lc":2,"lj":2,"bm":0,"nm":".primary","mn":"ADBE Vector Graphic - Stroke","hd":false,"cl":"primary"},{"ty":"tr","p":{"a":0,"k":[250,338.42],"ix":2},"a":{"a":0,"k":[0,0],"ix":1},"s":{"a":0,"k":[100,100],"ix":3},"r":{"a":0,"k":0,"ix":6},"o":{"a":0,"k":100,"ix":7},"sk":{"a":0,"k":0,"ix":4},"sa":{"a":0,"k":0,"ix":5},"nm":"Transform"}],"nm":"Group 6","np":2,"cix":2,"bm":0,"ix":6,"mn":"ADBE Vector Group","hd":false}],"ip":0,"op":300,"st":0,"ct":1,"bm":0}]}],"layers":[{"ddd":0,"ind":1,"ty":3,"nm":"control","sr":1,"ks":{"o":{"a":0,"k":0,"ix":11},"r":{"a":0,"k":0,"ix":10},"p":{"a":0,"k":[0,0],"ix":2,"l":2},"a":{"a":0,"k":[0,0,0],"ix":1,"l":2},"s":{"a":0,"k":[100,100,100],"ix":6,"l":2}},"ao":0,"ef":[{"ty":5,"nm":"stroke","np":3,"mn":"Pseudo/@@2rM+cO8uSNqO1PB56AbHMA","ix":1,"en":1,"ef":[{"ty":7,"nm":"Menu","mn":"Pseudo/@@2rM+cO8uSNqO1PB56AbHMA-0001","ix":1,"v":{"a":0,"k":2,"ix":1}}]},{"ty":5,"nm":"primary","np":3,"mn":"ADBE Color Control","ix":2,"en":1,"ef":[{"ty":2,"nm":"Color","mn":"ADBE Color Control-0001","ix":1,"v":{"a":0,"k":[0.070588238537,0.074509806931,0.192156866193,1],"ix":1}}]},{"ty":5,"nm":"secondary","np":3,"mn":"ADBE Color Control","ix":3,"en":1,"ef":[{"ty":2,"nm":"Color","mn":"ADBE Color Control-0001","ix":1,"v":{"a":0,"k":[0.031372550875,0.658823549747,0.541176497936,1],"ix":1}}]}],"ip":0,"op":221,"st":0,"bm":0},{"ddd":0,"ind":2,"ty":0,"nm":"in-reveal","refId":"comp_0","sr":1,"ks":{"o":{"a":0,"k":100,"ix":11},"r":{"a":0,"k":0,"ix":10},"p":{"a":0,"k":[215,215,0],"ix":2,"l":2},"a":{"a":0,"k":[215,215,0],"ix":1,"l":2},"s":{"a":0,"k":[100,100,100],"ix":6,"l":2}},"ao":0,"w":430,"h":430,"ip":0,"op":100,"st":0,"bm":0},{"ddd":0,"ind":3,"ty":0,"nm":"hover-pinch","refId":"comp_1","sr":1,"ks":{"o":{"a":0,"k":100,"ix":11},"r":{"a":0,"k":0,"ix":10},"p":{"a":0,"k":[215,215,0],"ix":2,"l":2},"a":{"a":0,"k":[215,215,0],"ix":1,"l":2},"s":{"a":0,"k":[100,100,100],"ix":6,"l":2}},"ao":0,"w":430,"h":430,"ip":100,"op":230,"st":100,"bm":0}],"markers":[{"tm":0,"cm":"in-reveal","dr":90},{"tm":100,"cm":"default:hover-pinch","dr":120}],"props":{}}